elastic/thrunting_tools/__init__.py
elastic/thrunting_tools/binaries/__init__.py
elastic/thrunting_tools/binaries/unmap_pe.py
elastic/thrunting_tools/common/__init__.py
elastic/thrunting_tools/common/elastic.py
elastic/thrunting_tools/common/settings.py
elastic/thrunting_tools/common/utils.py
elastic/thrunting_tools/compression/zlib_deflate.py
elastic/thrunting_tools/compression/zlib_inflate.py
elastic/thrunting_tools/eql_query.py
elastic/thrunting_tools/format/__init__.py
elastic/thrunting_tools/format/from_charcode.py
elastic/thrunting_tools/format/to_charcode.py
elastic/thrunting_tools/format/url_decode.py
elastic/thrunting_tools/format/url_encode.py
elastic/thrunting_tools/lucene_query.py
thrunting_tools-8.5.2.dist-info/entry_points.txt
thrunting_tools-8.5.2.dist-info/LICENSE
thrunting_tools-8.5.2.dist-info/WHEEL
thrunting_tools-8.5.2.dist-info/METADATA
thrunting_tools-8.5.2.dist-info/RECORD
