Metadata-Version: 2.1
Name: thrunting-tools
Version: 8.5.2
Summary: A collection of utilities to help with threat hunting on the command line.
Home-page: https://github.com/elastic/securitylabs-thrunting-tools
License: Apache-2.0
Keywords: elasticsearch,eql,lucene,command line
Author: Derek Ditch
Author-email: dcode@users.noreply.github.com
Requires-Python: >=3.10,<4.0
Classifier: Development Status :: 4 - Beta
Classifier: Environment :: Console
Classifier: Intended Audience :: Information Technology
Classifier: License :: OSI Approved :: Apache Software License
Classifier: Operating System :: OS Independent
Classifier: Programming Language :: Python :: 3
Classifier: Programming Language :: Python :: 3.10
Classifier: Programming Language :: Python :: 3.11
Classifier: Programming Language :: Python :: 3
Classifier: Topic :: Security
Classifier: Typing :: Typed
Requires-Dist: appdirs (>=1.4.4,<2.0.0)
Requires-Dist: elasticsearch (>=8.5.0,<9.0.0)
Requires-Dist: pefile (>=2022.5.30,<2023.0.0)
Requires-Dist: prompt-toolkit (>=3.0.32,<4.0.0)
Requires-Dist: pydantic (>=1.10.2,<2.0.0)
Requires-Dist: pygments (>=2.13.0,<3.0.0)
Requires-Dist: ruamel-yaml (>=0.17.21,<0.18.0)
Requires-Dist: scalpl (>=0.4.2,<0.5.0)
Requires-Dist: typer[all] (>=0.7.0,<0.8.0)
Project-URL: Bug Tracker, https://github.com/elastic/securitylabs-thrunting-tools/issues
Project-URL: Repository, https://github.com/elastic/securitylabs-thrunting-tools
